riboflow/__init__.py
riboflow/rnn_24_model.h5
riboflow/rnn_32_model.h5
riboflow-1.1.2.dist-info/LICENSE
riboflow-1.1.2.dist-info/METADATA
riboflow-1.1.2.dist-info/WHEEL
riboflow-1.1.2.dist-info/top_level.txt
riboflow-1.1.2.dist-info/RECORD
