Metadata-Version: 2.1
Name: riboflow
Version: 1.1.2
Summary: Classifying Putative Riboswitch Sequences
Home-page: https://github.com/RiboswitchClassifier/riboflow
Author: Ashok Palaniappan, Keshav Aditya R.P, Ramit Bharanikumar
Author-email: apalania@scbt.sastra.edu, keshavaditya26896@gmail.com, ramitb@rocketmail.com
License: UNKNOWN
Platform: UNKNOWN
Classifier: Programming Language :: Python :: 3
Classifier: License :: OSI Approved :: MIT License
Classifier: Operating System :: OS Independent
